cloud_aitools/main.py
cloud_aitools/handler/__init__.py
cloud_aitools/handler/cos_handler.py
cloud_aitools/handler/models.py
cloud_aitools/model/__init__.py
cloud_aitools/model/defaults.py
cloud_aitools/model/distribute.py
cloud_aitools/model/handler.py
cloud_aitools/model/models.py
cloud_aitools/utils/__init__.py
cloud_aitools/utils/async_downloader.py
cloud_aitools/utils/dns.py
cloud_aitools/utils/progress.py
cloud_aitools/utils/utils.py
cloud_aitools-2.1.0.dist-info/licenses/LICENSE
cloud_aitools-2.1.0.dist-info/METADATA
cloud_aitools-2.1.0.dist-info/WHEEL
cloud_aitools-2.1.0.dist-info/entry_points.txt
cloud_aitools-2.1.0.dist-info/top_level.txt
cloud_aitools-2.1.0.dist-info/RECORD
