Metadata-Version: 2.4
Name: cloud_aitools
Version: 2.1.0
Summary: cloud-aitools is a CLI tool for managing AI models on Tencent Cloud, providing high-performance upload, download and model management capabilities.
Requires-Python: >=3.12
License-File: LICENSE
Requires-Dist: aiohttp>=3.11.18
Requires-Dist: alive-progress>=3.2.0
Requires-Dist: anyio>=4.9.0
Requires-Dist: blake3>=1.0.4
Requires-Dist: build>=1.2.2.post1
Requires-Dist: certifi>=2025.1.31
Requires-Dist: cos-python-sdk-v5>=1.9.36
Requires-Dist: minio>=7.2.15
Requires-Dist: pydantic>=2.11.3
Requires-Dist: python-dotenv>=1.1.0
Requires-Dist: tqdm>=4.67.1
Requires-Dist: twine>=6.1.0
Requires-Dist: typer>=0.15.2
Requires-Dist: urllib3>=2.4.0
Requires-Dist: click<8.2.0,>=8.1.6
Dynamic: license-file
